{
  "data": {
    "all_awardings": [],
    "approved_at_utc": null,
    "approved_by": null,
    "archived": false,
    "associated_award": null,
    "author": "myneighborscatismine",
    "author_flair_background_color": null,
    "author_flair_css_class": null,
    "author_flair_richtext": [],
    "author_flair_template_id": null,
    "author_flair_text": null,
    "author_flair_text_color": null,
    "author_flair_type": "text",
    "author_fullname": "t2_3n7wenjk",
    "author_is_blocked": false,
    "author_patreon_flair": false,
    "author_premium": false,
    "awarders": [],
    "banned_at_utc": null,
    "banned_by": null,
    "body": "Why did the man follow you home :( I've had men follow me but not home luckily.. Although once he would if I didn't make a quick turn and lost him. This kind of situations are so scary.",
    "body_html": "\u0026lt;div class=\"md\"\u0026gt;\u0026lt;p\u0026gt;Why did the man follow you home :( I\u0026amp;#39;ve had men follow me but not home luckily.. Although once he would if I didn\u0026amp;#39;t make a quick turn and lost him. This kind of situations are so scary.\u0026lt;/p\u0026gt;\n\u0026lt;/div\u0026gt;",
    "can_gild": true,
    "can_mod_post": false,
    "collapsed": false,
    "collapsed_because_crowd_control": null,
    "collapsed_reason": null,
    "collapsed_reason_code": null,
    "comment_type": null,
    "controversiality": 0,
    "created": 1679198069,
    "created_utc": 1679198069,
    "depth": 0,
    "distinguished": null,
    "downs": 0,
    "edited": false,
    "gilded": 0,
    "gildings": {},
    "id": "jcs8hlr",
    "is_submitter": false,
    "likes": null,
    "link_id": "t3_11v738l",
    "locked": false,
    "mod_note": null,
    "mod_reason_by": null,
    "mod_reason_title": null,
    "mod_reports": [],
    "name": "t1_jcs8hlr",
    "no_follow": false,
    "num_reports": null,
    "parent_id": "t3_11v738l",
    "permalink": "/r/aww/comments/11v738l/a_man_followed_me_home_and_these_two_logs_chased/jcs8hlr/",
    "removal_reason": null,
    "replies": {
      "data": {
        "after": null,
        "before": null,
        "children": [
          {
            "data": {
              "all_awardings": [],
              "approved_at_utc": null,
              "approved_by": null,
              "archived": false,
              "associated_award": null,
              "author": "Ok_Balance8844",
              "author_flair_background_color": null,
              "author_flair_css_class": null,
              "author_flair_richtext": [],
              "author_flair_template_id": null,
              "author_flair_text": null,
              "author_flair_text_color": null,
              "author_flair_type": "text",
              "author_fullname": "t2_lna6rrw5",
              "author_is_blocked": false,
              "author_patreon_flair": false,
              "author_premium": false,
              "awarders": [],
              "banned_at_utc": null,
              "banned_by": null,
              "body": "Yeah when I’m being followed I tend to go to a more public place like a restaurant or something.\n\nThey probably weren’t close to anything though which is a shame.",
              "body_html": "\u0026lt;div class=\"md\"\u0026gt;\u0026lt;p\u0026gt;Yeah when I’m being followed I tend to go to a more public place like a restaurant or something.\u0026lt;/p\u0026gt;\n\n\u0026lt;p\u0026gt;They probably weren’t close to anything though which is a shame.\u0026lt;/p\u0026gt;\n\u0026lt;/div\u0026gt;",
              "can_gild": true,
              "can_mod_post": false,
              "collapsed": false,
              "collapsed_because_crowd_control": null,
              "collapsed_reason": null,
              "collapsed_reason_code": null,
              "comment_type": null,
              "controversiality": 0,
              "created": 1679202437,
              "created_utc": 1679202437,
              "depth": 1,
              "distinguished": null,
              "downs": 0,
              "edited": false,
              "gilded": 0,
              "gildings": {},
              "id": "jcsfmq7",
              "is_submitter": false,
              "likes": null,
              "link_id": "t3_11v738l",
              "locked": false,
              "mod_note": null,
              "mod_reason_by": null,
              "mod_reason_title": null,
              "mod_reports": [],
              "name": "t1_jcsfmq7",
              "no_follow": false,
              "num_reports": null,
              "parent_id": "t1_jcs8hlr",
              "permalink": "/r/aww/comments/11v738l/a_man_followed_me_home_and_these_two_logs_chased/jcsfmq7/",
              "removal_reason": null,
              "replies": {
                "data": {
                  "after": null,
                  "before": null,
                  "children": [
                    {
                      "data": {
                        "all_awardings": [],
                        "approved_at_utc": null,
                        "approved_by": null,
                        "archived": false,
                        "associated_award": null,
                        "author": "ferretsRfantastic",
                        "author_flair_background_color": null,
                        "author_flair_css_class": null,
                        "author_flair_richtext": [],
                        "author_flair_template_id": null,
                        "author_flair_text": null,
                        "author_flair_text_color": null,
                        "author_flair_type": "text",
                        "author_fullname": "t2_flube",
                        "author_is_blocked": false,
                        "author_patreon_flair": false,
                        "author_premium": false,
                        "awarders": [],
                        "banned_at_utc": null,
                        "banned_by": null,
                        "body": "The few times I've felt that I've been followed, in my car, I've rerouted to the closest police station. When you pull into those, that often deters the creeps.",
                        "body_html": "\u0026lt;div class=\"md\"\u0026gt;\u0026lt;p\u0026gt;The few times I\u0026amp;#39;ve felt that I\u0026amp;#39;ve been followed, in my car, I\u0026amp;#39;ve rerouted to the closest police station. When you pull into those, that often deters the creeps.\u0026lt;/p\u0026gt;\n\u0026lt;/div\u0026gt;",
                        "can_gild": true,
                        "can_mod_post": false,
                        "collapsed": false,
                        "collapsed_because_crowd_control": null,
                        "collapsed_reason": null,
                        "collapsed_reason_code": null,
                        "comment_type": null,
                        "controversiality": 0,
                        "created": 1679209432,
                        "created_utc": 1679209432,
                        "depth": 2,
                        "distinguished": null,
                        "downs": 0,
                        "edited": false,
                        "gilded": 0,
                        "gildings": {},
                        "id": "jcsota7",
                        "is_submitter": false,
                        "likes": null,
                        "link_id": "t3_11v738l",
                        "locked": false,
                        "mod_note": null,
                        "mod_reason_by": null,
                        "mod_reason_title": null,
                        "mod_reports": [],
                        "name": "t1_jcsota7",
                        "no_follow": false,
                        "num_reports": null,
                        "parent_id": "t1_jcsfmq7",
                        "permalink": "/r/aww/comments/11v738l/a_man_followed_me_home_and_these_two_logs_chased/jcsota7/",
                        "removal_reason": null,
                        "replies": {
                          "data": {
                            "after": null,
                            "before": null,
                            "children": [
                              {
                                "data": {
                                  "all_awardings": [],
                                  "approved_at_utc": null,
                                  "approved_by": null,
                                  "archived": false,
                                  "associated_award": null,
                                  "author": "Ok_Balance8844",
                                  "author_flair_background_color": null,
                                  "author_flair_css_class": null,
                                  "author_flair_richtext": [],
                                  "author_flair_template_id": null,
                                  "author_flair_text": null,
                                  "author_flair_text_color": null,
                                  "author_flair_type": "text",
                                  "author_fullname": "t2_lna6rrw5",
                                  "author_is_blocked": false,
                                  "author_patreon_flair": false,
                                  "author_premium": false,
                                  "awarders": [],
                                  "banned_at_utc": null,
                                  "banned_by": null,
                                  "body": "I usually go to the closest restaurant or any other public place. Luckily I’m in a really populated area so someone will hear me lol.",
                                  "body_html": "\u0026lt;div class=\"md\"\u0026gt;\u0026lt;p\u0026gt;I usually go to the closest restaurant or any other public place. Luckily I’m in a really populated area so someone will hear me lol.\u0026lt;/p\u0026gt;\n\u0026lt;/div\u0026gt;",
                                  "can_gild": true,
                                  "can_mod_post": false,
                                  "collapsed": false,
                                  "collapsed_because_crowd_control": null,
                                  "collapsed_reason": null,
                                  "collapsed_reason_code": null,
                                  "comment_type": null,
                                  "controversiality": 0,
                                  "created": 1679213580,
                                  "created_utc": 1679213580,
                                  "depth": 3,
                                  "distinguished": null,
                                  "downs": 0,
                                  "edited": false,
                                  "gilded": 0,
                                  "gildings": {},
                                  "id": "jcstjfs",
                                  "is_submitter": false,
                                  "likes": null,
                                  "link_id": "t3_11v738l",
                                  "locked": false,
                                  "mod_note": null,
                                  "mod_reason_by": null,
                                  "mod_reason_title": null,
                                  "mod_reports": [],
                                  "name": "t1_jcstjfs",
                                  "no_follow": false,
                                  "num_reports": null,
                                  "parent_id": "t1_jcsota7",
                                  "permalink": "/r/aww/comments/11v738l/a_man_followed_me_home_and_these_two_logs_chased/jcstjfs/",
                                  "removal_reason": null,
                                  "replies": {
                                    "data": {
                                      "after": null,
                                      "before": null,
                                      "children": [
                                        {
                                          "data": {
                                            "children": [
                                              "jcsu1bt"
                                            ],
                                            "count": 1,
                                            "depth": 4,
                                            "id": "jcsu1bt",
                                            "name": "t1_jcsu1bt",
                                            "parent_id": "t1_jcstjfs"
                                          },
                                          "kind": "more"
                                        }
                                      ],
                                      "dist": null,
                                      "geo_filter": "",
                                      "modhash": ""
                                    },
                                    "kind": "Listing"
                                  },
                                  "report_reasons": null,
                                  "saved": false,
                                  "score": 1,
                                  "score_hidden": true,
                                  "send_replies": true,
                                  "stickied": false,
                                  "subreddit": "aww",
                                  "subreddit_id": "t5_2qh1o",
                                  "subreddit_name_prefixed": "r/aww",
                                  "subreddit_type": "public",
                                  "top_awarded_type": null,
                                  "total_awards_received": 0,
                                  "treatment_tags": [],
                                  "unrepliable_reason": null,
                                  "ups": 1,
                                  "user_reports": []
                                },
                                "kind": "t1"
                              }
                            ],
                            "dist": null,
                            "geo_filter": "",
                            "modhash": ""
                          },
                          "kind": "Listing"
                        },
                        "report_reasons": null,
                        "saved": false,
                        "score": 1,
                        "score_hidden": true,
                        "send_replies": true,
                        "stickied": false,
                        "subreddit": "aww",
                        "subreddit_id": "t5_2qh1o",
                        "subreddit_name_prefixed": "r/aww",
                        "subreddit_type": "public",
                        "top_awarded_type": null,
                        "total_awards_received": 0,
                        "treatment_tags": [],
                        "unrepliable_reason": null,
                        "ups": 1,
                        "user_reports": []
                      },
                      "kind": "t1"
                    },
                    {
                      "data": {
                        "children": [
                          "jcsjrj0"
                        ],
                        "count": 1,
                        "depth": 2,
                        "id": "jcsjrj0",
                        "name": "t1_jcsjrj0",
                        "parent_id": "t1_jcsfmq7"
                      },
                      "kind": "more"
                    }
                  ],
                  "dist": null,
                  "geo_filter": "",
                  "modhash": ""
                },
                "kind": "Listing"
              },
              "report_reasons": null,
              "saved": false,
              "score": 1,
              "score_hidden": true,
              "send_replies": true,
              "stickied": false,
              "subreddit": "aww",
              "subreddit_id": "t5_2qh1o",
              "subreddit_name_prefixed": "r/aww",
              "subreddit_type": "public",
              "top_awarded_type": null,
              "total_awards_received": 0,
              "treatment_tags": [],
              "unrepliable_reason": null,
              "ups": 1,
              "user_reports": []
            },
            "kind": "t1"
          },
          {
            "data": {
              "all_awardings": [],
              "approved_at_utc": null,
              "approved_by": null,
              "archived": false,
              "associated_award": null,
              "author": "doesamulletmakeaman",
              "author_flair_background_color": null,
              "author_flair_css_class": null,
              "author_flair_richtext": [],
              "author_flair_template_id": null,
              "author_flair_text": null,
              "author_flair_text_color": null,
              "author_flair_type": "text",
              "author_fullname": "t2_1q6omeco",
              "author_is_blocked": false,
              "author_patreon_flair": false,
              "author_premium": true,
              "awarders": [],
              "banned_at_utc": null,
              "banned_by": null,
              "body": "My garage door opener recently punked out so I had to get out and open it to pull in and he saw my car as he drove by and pulled in as the door was closing. That’s when he came up on the porch. It was very very unexpected lol",
              "body_html": "\u0026lt;div class=\"md\"\u0026gt;\u0026lt;p\u0026gt;My garage door opener recently punked out so I had to get out and open it to pull in and he saw my car as he drove by and pulled in as the door was closing. That’s when he came up on the porch. It was very very unexpected lol\u0026lt;/p\u0026gt;\n\u0026lt;/div\u0026gt;",
              "can_gild": true,
              "can_mod_post": false,
              "collapsed": false,
              "collapsed_because_crowd_control": null,
              "collapsed_reason": null,
              "collapsed_reason_code": null,
              "comment_type": null,
              "controversiality": 0,
              "created": 1679252137,
              "created_utc": 1679252137,
              "depth": 1,
              "distinguished": null,
              "downs": 0,
              "edited": false,
              "gilded": 0,
              "gildings": {},
              "id": "jcuthdt",
              "is_submitter": true,
              "likes": null,
              "link_id": "t3_11v738l",
              "locked": false,
              "mod_note": null,
              "mod_reason_by": null,
              "mod_reason_title": null,
              "mod_reports": [],
              "name": "t1_jcuthdt",
              "no_follow": true,
              "num_reports": null,
              "parent_id": "t1_jcs8hlr",
              "permalink": "/r/aww/comments/11v738l/a_man_followed_me_home_and_these_two_logs_chased/jcuthdt/",
              "removal_reason": null,
              "replies": "",
              "report_reasons": null,
              "saved": false,
              "score": 1,
              "score_hidden": true,
              "send_replies": true,
              "stickied": false,
              "subreddit": "aww",
              "subreddit_id": "t5_2qh1o",
              "subreddit_name_prefixed": "r/aww",
              "subreddit_type": "public",
              "top_awarded_type": null,
              "total_awards_received": 0,
              "treatment_tags": [],
              "unrepliable_reason": null,
              "ups": 1,
              "user_reports": []
            },
            "kind": "t1"
          }
        ],
        "dist": null,
        "geo_filter": "",
        "modhash": ""
      },
      "kind": "Listing"
    },
    "report_reasons": null,
    "saved": false,
    "score": 1,
    "score_hidden": true,
    "send_replies": true,
    "stickied": false,
    "subreddit": "aww",
    "subreddit_id": "t5_2qh1o",
    "subreddit_name_prefixed": "r/aww",
    "subreddit_type": "public",
    "top_awarded_type": null,
    "total_awards_received": 0,
    "treatment_tags": [],
    "unrepliable_reason": null,
    "ups": 1,
    "user_reports": []
  },
  "kind": "t1"
}